simple_twitch_stream_receiver/__init__.py
simple_twitch_stream_receiver/exceptions.py
simple_twitch_stream_receiver/receiver.py
simple_twitch_stream_receiver-0.0.2.dist-info/LICENSE
simple_twitch_stream_receiver-0.0.2.dist-info/METADATA
simple_twitch_stream_receiver-0.0.2.dist-info/WHEEL
simple_twitch_stream_receiver-0.0.2.dist-info/top_level.txt
simple_twitch_stream_receiver-0.0.2.dist-info/RECORD
