Metadata-Version: 2.1
Name: simple-twitch-stream-receiver
Version: 0.0.2
Summary: A tiny package for creating a generator of np.ndarray frames from twitch stream
Author-email: Jan Pawłowski <janpawlowskiof@gmail.com>
Project-URL: Homepage, https://github.com/janpawlowskiof/simple_twitch_stream_receiver
Project-URL: Bug Tracker, https://github.com/janpawlowskiof/simple_twitch_stream_receiver/issues
Classifier: Programming Language :: Python :: 3
Classifier: License :: OSI Approved :: MIT License
Classifier: Operating System :: OS Independent
Requires-Python: >=3.7
License-File: LICENSE
Requires-Dist: setuptools
Requires-Dist: streamlink (>=5.1.2)
Requires-Dist: ffmpeg-python (>=0.2.0)
Requires-Dist: numpy
